cardonnay/__init__.py
cardonnay/ca_utils.py
cardonnay/cli_control.py
cardonnay/cli_create.py
cardonnay/cli_inspect.py
cardonnay/color_logger.py
cardonnay/colors.py
cardonnay/consts.py
cardonnay/helpers.py
cardonnay/inspect_instance.py
cardonnay/local_scripts.py
cardonnay/main.py
cardonnay/structs.py
cardonnay/ttypes.py
cardonnay-0.2.15.dist-info/licenses/LICENSE
cardonnay_scripts/__init__.py
cardonnay_scripts/scripts/common/common-start-fast
cardonnay_scripts/scripts/common/common-start-slow
cardonnay_scripts/scripts/common/common.sh
cardonnay_scripts/scripts/common/postgres-setup.sh
cardonnay_scripts/scripts/common/run-cardano-dbsync
cardonnay_scripts/scripts/common/run-cardano-smash
cardonnay_scripts/scripts/common/run-cardano-submit-api
cardonnay_scripts/scripts/common/stop-cluster
cardonnay_scripts/scripts/conway_fast/byron-params.json
cardonnay_scripts/scripts/conway_fast/cardano-node-bft1
cardonnay_scripts/scripts/conway_fast/dbsync-config.yaml
cardonnay_scripts/scripts/conway_fast/genesis.alonzo.spec.json
cardonnay_scripts/scripts/conway_fast/genesis.conway.spec.json
cardonnay_scripts/scripts/conway_fast/genesis.dijkstra.spec.json
cardonnay_scripts/scripts/conway_fast/genesis.spec.json
cardonnay_scripts/scripts/conway_fast/start-cluster
cardonnay_scripts/scripts/conway_fast/submit-api-config.json
cardonnay_scripts/scripts/conway_fast/template-cardano-node-pool
cardonnay_scripts/scripts/conway_fast/template-config.json
cardonnay_scripts/scripts/conway_fast/testnet.json
cardonnay_scripts/scripts/conway_slow/byron-params.json
cardonnay_scripts/scripts/conway_slow/cardano-node-bft1
cardonnay_scripts/scripts/conway_slow/cost_models_list.json
cardonnay_scripts/scripts/conway_slow/dbsync-config.yaml
cardonnay_scripts/scripts/conway_slow/genesis.alonzo.spec.json
cardonnay_scripts/scripts/conway_slow/genesis.conway.spec.json
cardonnay_scripts/scripts/conway_slow/genesis.dijkstra.spec.json
cardonnay_scripts/scripts/conway_slow/genesis.spec.json
cardonnay_scripts/scripts/conway_slow/start-cluster
cardonnay-0.2.15.dist-info/METADATA
cardonnay-0.2.15.dist-info/WHEEL
cardonnay-0.2.15.dist-info/entry_points.txt
cardonnay-0.2.15.dist-info/top_level.txt
cardonnay-0.2.15.dist-info/RECORD
