Metadata-Version: 2.4
Name: cardonnay
Version: 0.2.15
Summary: Cardano Local Testnet
Author-email: Martin Kourim <martin.kourim@iohk.io>
License-Expression: Apache-2.0
Project-URL: homepage, https://github.com/IntersectMBO/cardonnay
Project-URL: documentation, https://github.com/IntersectMBO/cardonnay
Project-URL: repository, https://github.com/IntersectMBO/cardonnay
Keywords: cardano,cardano-node,cardano-cli
Classifier: Topic :: Software Development :: Libraries :: Python Modules
Classifier: Programming Language :: Python :: 3
Classifier: Programming Language :: Python :: 3.9
Classifier: Programming Language :: Python :: 3.10
Classifier: Programming Language :: Python :: 3.11
Classifier: Programming Language :: Python :: 3.12
Classifier: Programming Language :: Python :: 3.13
Classifier: Intended Audience :: Developers
Requires-Python: >=3.9
License-File: LICENSE
Requires-Dist: setuptools<80.9
Requires-Dist: supervisor
Requires-Dist: click>=7.0
Requires-Dist: pygments>=2.0
Requires-Dist: pydantic>=2.0
Requires-Dist: filelock>=3.0
Dynamic: license-file
